{
  "spec": {
    "manufacturer": "manufacturer1",
    "model": "endt44198",
    "batch": "2024",
    "chemistry": "li-ion",
    "form_factor": "pouch",
    "tab_design": "end-tab",
    "nominal_voltage_v": 3.83,
    "rated_capacity_ah": 3.00,
    "rated_energy_wh": 11.5,
    "mass_g": 48.0,
    "volume_l": 0.0182,
    "pe_materials": ["lco"],
    "ne_materials": ["graphite"]
  },
  "ids": [
    "A00A4",
    "A00A5",
    "A00AC",
    "A00B1",
    "A00B7",
    "A00BA",
    "A00C0",
    "A00CD",
    "A00D4",
    "A00D7",
    "A00F6",
    "A00F7",
    "A00F8",
    "A00FD",
    "A0006",
    "A0007",
    "A001B",
    "A0011",
    "A0019",
    "A003B",
    "A004C",
    "A0048",
    "A0050",
    "A006B",
    "A006C",
    "A0064",
    "A0065",
    "A0067",
    "A007A",
    "A007B",
    "A007F",
    "A0070",
    "A0080",
    "A0086",
    "A009A",
    "A009E",
    "A009F",
    "A0095",
    "A0096",
    "A0098",
    "A01AA",
    "A01AB",
    "A01AF",
    "A01B0",
    "A01B2",
    "A01B3",
    "A01C2",
    "A01C4",
    "A01D2",
    "A01D3",
    "A01D7",
    "A01DD",
    "A01E1",
    "A01E5",
    "A01E8",
    "A010D",
    "A0102",
    "A0113",
    "A0116",
    "A012E",
    "A012F",
    "A014A",
    "A0146",
    "A016C",
    "A0172",
    "A0174",
    "A0175",
    "A0176",
    "A0179",
    "A018B",
    "A018C",
    "A018F",
    "A0180",
    "A0187",
    "A0189",
    "A0193",
    "A0195",
    "A02A4",
    "A022A",
    "A0254",
    "A0283",
    "A029C",
    "A029D",
    "A0294",
    "A0299"
  ]
}